pico_up/__init__.py
pico_up/cli.py
pico_up/command_help.py
pico_up/commands/__init__.py
pico_up/commands/base.py
pico_up/commands/command_free.py
pico_up/commands/command_image.py
pico_up/commands/command_init.py
pico_up/commands/command_push.py
pico_up/commands/command_version.py
pico_up/commands/command_wipe.py
pico_up/util/__init__.py
pico_up/util/build.py
pico_up/util/configuration.py
pico_up/util/errors.py
pico_up/util/files.py
pico_up_modules/__init__.py
pico_up_modules/free_commands.py
pico_up_modules/msgpack_loads.py
pico_up-0.0.9.dist-info/LICENSE
pico_up-0.0.9.dist-info/METADATA
pico_up-0.0.9.dist-info/WHEEL
pico_up-0.0.9.dist-info/entry_points.txt
pico_up-0.0.9.dist-info/top_level.txt
pico_up-0.0.9.dist-info/RECORD
