Metadata-Version: 2.1
Name: pico-up
Version: 0.0.9
Summary: Command line tools for developing applications for the Raspberry Pico
License-File: LICENSE
Requires-Dist: Pillow (==9.4.0)
Requires-Dist: mpremote (==0.4.0)
Requires-Dist: mpy-cross-v6 (==1.0.1)
Requires-Dist: numpy (==1.24.2)
Requires-Dist: python-minifier (==2.8.1)
Requires-Dist: termcolor (==2.2.0)
Requires-Dist: u-msgpack-python (==2.7.2)
